CHANGES.txt
LICENSE.txt
MANIFEST.in
README
README.rst
setup.py
Embeder.egg-info/PKG-INFO
Embeder.egg-info/SOURCES.txt
Embeder.egg-info/dependency_links.txt
Embeder.egg-info/requires.txt
Embeder.egg-info/top_level.txt
embeder/__init__.py
embeder/embed.py
embeder/backends/__init__.py
embeder/backends/default.py
embeder/backends/oembed.py
embeder/backends/opengraph.py
embeder/backends/twitter.py
embeder/test/__init__.py
embeder/test/test_api.py