Metadata-Version: 1.0
Name: Embeder
Version: 0.1.1
Summary: Retrieves useful information about a link.
Home-page: https://github.com/fgaudin/Embeder
Author: Francois Gaudin
Author-email: contact@francoisgaudin.com
License: LICENSE.txt
Platform: UNKNOWN
